{
  "prompt_type": "cot",
  "model_name": "llama3.2:1b-instruct-q4_K_M",
  "start_time": "2025-01-04 19:52:57.752060",
  "end_time": "2025-01-04 19:53:28.934205",
  "total_attempts": 60,
  "successful_attempts": 60,
  "failed_attempts": 0,
  "timeout_attempts": 0,
  "avg_execution_time": 0.519179085890452,
  "median_execution_time": 0.48018407821655273,
  "sd_execution_time": 0.08521853406548377,
  "timeout_stats": {
    "total_timeouts": 0,
    "avg_timeout_duration": 0.0,
    "max_timeout_duration": 0.0,
    "total_timeout_duration": 0.0
  },
  "meta_data_averages": {
    "done": 1.0,
    "total_duration": 516618516.28333336,
    "load_duration": 19409531.433333334,
    "prompt_eval_count": 142.4,
    "prompt_eval_duration": 63550000.0,
    "eval_count": 17.283333333333335,
    "eval_duration": 431983333.3333333
  },
  "meta_data_sd": {
    "done": 0.0,
    "total_duration": 85212093.85122213,
    "load_duration": 2525997.6326527237,
    "prompt_eval_count": 0.49403218175557095,
    "prompt_eval_duration": 84427568.99721596,
    "eval_count": 0.4903014177279,
    "eval_duration": 14545651.882970558
  },
  "prediction_accuracy": 45.0,
  "prediction_distribution": {
    "YES": 39,
    "NO": 21
  },
  "actual_distribution": {
    "NO": 48,
    "YES": 12
  },
  "confusion_matrix": {
    "tp": 9,
    "tn": 18,
    "fp": 30,
    "fn": 3
  },
  "auc_roc": 0.47829861111111116
}