{
  "decision": {
    "prediction": "YES",
    "confidence": 85,
    "id": 753,
    "actual": "NO",
    "correct": "NO"
  },
  "meta_data": {
    "model": "reflection:70b-q4_K_M",
    "created_at": "2025-02-06T16:05:30.914540362Z",
    "done_reason": "stop",
    "done": true,
    "total_duration": 220.220537945,
    "load_duration": 0.018761969,
    "prompt_eval_count": 340,
    "prompt_eval_duration": 1.662,
    "eval_count": 1295,
    "eval_duration": 218.538
  },
  "response": {
    "raw_message_text": "<thinking>\nTo solve this problem, I'll need to analyze each piece of information provided about the individual and assess its potential impact on recidivism risk. Then, I'll use these assessments to make a prediction about 3-year rearrest recidivism. Let's break it down step by step:\n\n1. Analyze demographic factors:\n   - Age: 19 (young adult)\n   - Race: White\n   - Height and weight: 6'0\", 230 lbs\n\n2. Examine criminal history:\n   - Arrests: 2 times\n   - Convictions: At least 1\n\n3. Evaluate social and family factors:\n   - Marital status: Never married\n   - Living situation: Alone\n   - Family background: Lived with both biological parents in a household of size 4\n\n4. Assess educational and employment factors:\n   - Education: No high school diploma or GED, not enrolled in college\n   - Employment: Held only 1 job during the year\n\n5. Consider substance use and mental health:\n   - Drug use: Past four years (marijuana and cocaine), frequent use in past month\n   - Mental state: Felt down in dumps all of last month\n\n6. Evaluate spiritual beliefs:\n   - Belief about God's influence on personal life\n\n7. Assign relative weights to each factor based on their potential impact on recidivism risk.\n\n8. Use these weighted factors to make a prediction about 3-year rearrest recidivism and estimate confidence in the prediction.\n\nLet's go through this analysis:\n\n1. Demographic factors:\n   - Age: High (young adults are more likely to reoffend)\n   - Race: Low (race alone is not a strong predictor of recidivism)\n   - Height and weight: Low (physical attributes don't strongly correlate with recidivism)\n\n2. Criminal history:\n   - Arrests: Medium-High (multiple arrests indicate potential for future criminal behavior)\n   - Convictions: High (at least one conviction increases likelihood of future offenses)\n\n3. Social and family factors:\n   - Marital status: Low-Medium (being unmarried at 19 is common, but lack of stable relationships can be a risk factor)\n   - Living situation: Medium-High (living alone may indicate social isolation or lack of support system)\n   - Family background: Low (stable childhood environment)\n\n4. Educational and employment factors:\n   - Education: High (lack of high school diploma or GED significantly increases recidivism risk)\n   - Employment: High (unstable job history is a strong predictor of recidivism)\n\n5. Substance use and mental health:\n   - Drug use: Very High (frequent drug use, especially multiple substances, strongly correlates with recidivism)\n   - Mental state: Medium-High (persistent feelings of depression can contribute to criminal behavior)\n\n6. Spiritual beliefs:\n   - Belief about God's influence: Low-Medium (spiritual beliefs alone are not strong predictors of recidivism)\n\n<reflection>\nUpon reflection, the analysis seems comprehensive and considers all provided factors. However, it might be beneficial to emphasize the cumulative effect of multiple risk factors rather than focusing solely on individual factors. Additionally, we should consider that while some factors may have a low or medium weight individually, their combined impact could significantly increase recidivism risk.\n</reflection>\n\nNow, let's use this analysis to make a prediction and estimate confidence:\n\nPrediction: YES (likely to be rearrested within 3 years)\nConfidence: 85%\n\nThe combination of multiple high-risk factors such as young age, lack of education, unstable employment history, frequent drug use, and potential mental health issues strongly suggests an increased likelihood of recidivism. While some factors like race and spiritual beliefs have lower weights, the cumulative effect of all risk factors points towards a higher probability of rearrest.\n\n</thinking>\n\n<output>\n{\n  \"risk_factors\": [\n    (\"Age\", \"high\", \"Young adults are more likely to reoffend\"),\n    (\"Race\", \"low\", \"Race alone is not a strong predictor of recidivism\"),\n    (\"Height and weight\", \"low\", \"Physical attributes don't strongly correlate with recidivism\"),\n    (\"Arrest history\", \"medium-high\", \"Multiple arrests indicate potential for future criminal behavior\"),\n    (\"Conviction history\", \"high\", \"At least one conviction increases likelihood of future offenses\"),\n    (\"Marital status\", \"low-medium\", \"Being unmarried at 19 is common, but lack of stable relationships can be a risk factor\"),\n    (\"Living situation\", \"medium-high\", \"Living alone may indicate social isolation or lack of support system\"),\n    (\"Family background\", \"low\", \"Stable childhood environment\"),\n    (\"Education\", \"high\", \"Lack of high school diploma or GED significantly increases recidivism risk\"),\n    (\"Employment history\", \"high\", \"Unstable job history is a strong predictor of recidivism\"),\n    (\"Substance use\", \"very high\", \"Frequent drug use, especially multiple substances, strongly correlates with recidivism\"),\n    (\"Mental state\", \"medium-high\", \"Persistent feelings of depression can contribute to criminal behavior\"),\n    (\"Spiritual beliefs\", \"low-medium\", \"Spiritual beliefs alone are not strong predictors of recidivism\")\n  ],\n  \"prediction\": \"YES\",\n  \"confidence\": 85\n}\n\nThis assessment takes into account multiple factors that contribute to the individual's risk of rearrest within three years. The combination of high-risk factors such as young age, lack of education, unstable employment history, frequent drug use, and potential mental health issues strongly suggests an increased likelihood of recidivism.\n\nThe highest weighted factors include:\n1. Lack of education (no high school diploma or GED)\n2. Unstable employment history\n3. Frequent substance use (marijuana and cocaine)\n4. Young age\n5. Conviction history\n\nThese factors, along with others like living alone and potential mental health issues, contribute to a cumulative risk profile that indicates a higher probability of rearrest within the next three years.\n\nIt's important to note that while some factors like race and spiritual beliefs have lower weights individually, their combined impact should not be overlooked. The overall assessment suggests an 85% confidence level in predicting recidivism based on these factors.\n\n</output>",
    "normalized_prediction": "YES"
  },
  "evaluation": {
    "timestamp": "20250206_110530_916818",
    "model": "reflection:70b-q4_K_M",
    "prompt_type": "PromptType.COT",
    "row_id": 753,
    "prediction_matches_actual": "NO",
    "repeat_index": 0
  },
  "prompt": {
    "system": "You are a highly experienced criminal justice risk assessment expert\nemploying advanced statistical and judicial knowledge.\n",
    "user": "You are a criminal risk assessment expert. Step back, take a deep breath and carefully think step by step to assign a relative weight [low, medium, high] to each risk factor before using them to collectively predict 3-year rearrest recidivism:\nThe person is a 19-year-old male who identifies himself as White. He has been arrested 2 times and has been convicted. He is 6 feet 0 inches and weighs 230 lbs. He has never been married and is currently living alone. He does not have a high school diploma or GED certificate and is not enrolled in college. He has held 1 job during the year. He has used drugs in the past four years (marijuana and cocaine) and all of the time during the past month he has felt so down in the dumps that nothing could cheer him up. At a young age, he lived with both of his biological parents in a household of size 4. He considers that God has nothing to do with what happens to him personally.\n\nAfter your analysis, you must respond ONLY with a JSON object in exactly this format, with no additional text:\n\n{\n  \"risk_factors\": [\n    (\"factor1\", \"low\"|\"medium\"|\"high\", \"textual reasoning\"),\n    (\"factor2\", \"low\"|\"medium\"|\"high\", \"textual reasoning\"),\n    ...\n  ],\n  \"prediction\": \"YES\" or \"NO\",\n  \"confidence\": number between 0 and 100\n}\n"
  }
}