{
  "prediction": "NO",
  "confidence": 80,
  "risk_factors": [
    {
      "factor": "age",
      "weight": "low",
      "reasoning": "At 18, he is considered a young adult and may not have the life experience to warrant rearrest."
    },
    {
      "factor": "education",
      "weight": "medium",
      "reasoning": "Although he has held one job, his lack of education may indicate underlying issues with motivation or self-improvement."
    },
    {
      "factor": "family circumstances",
      "weight": "high",
      "reasoning": "Living in a household of size 4 and having no married parents may suggest a history of instability or neglect."
    },
    {
      "factor": "employment status",
      "weight": "low",
      "reasoning": "His lack of job experience and current unemployment status indicate potential for future instability."
    },
    {
      "factor": "substance abuse",
      "weight": "medium",
      "reasoning": "Although he has not felt depressed, his past use of drugs may be a concern."
    },
    {
      "factor": "moral character",
      "weight": "low",
      "reasoning": "His history of living with biological parents and considering God's role in his life may suggest an element of faith or moral guidance."
    },
    {
      "factor": "physical appearance",
      "weight": "high",
      "reasoning": "His height and weight may indicate potential health risks or a higher likelihood of violence."
    },
    {
      "factor": "age of arrest",
      "weight": "low",
      "reasoning": "He is only 18, so he has not yet faced the consequences of his actions."
    },
    {
      "factor": "length of previous arrests",
      "weight": "high",
      "reasoning": "His history of multiple arrests within a short period may indicate underlying issues with impulsivity or poor decision-making."
    }
  ]
}