{
  "prompt_type": "PromptType.SYSTEM1",
  "model_name": "falcon3:10b-instruct-fp16",
  "start_time": "2025-01-05 10:22:14.431200",
  "end_time": "2025-01-05 10:23:40.274956",
  "total_attempts": 100,
  "successful_attempts": 100,
  "failed_attempts": 0,
  "timeout_attempts": 0,
  "avg_execution_time": 0.8568234443664551,
  "median_execution_time": 0.6972453594207764,
  "sd_execution_time": 1.8394515083966096,
  "timeout_stats": {
    "total_timeouts": 0,
    "avg_timeout_duration": 0.0,
    "max_timeout_duration": 0.0,
    "total_timeout_duration": 0.0
  },
  "meta_data_averages": {
    "done": 1.0,
    "total_duration": 854648819.12,
    "load_duration": 203444427.54,
    "prompt_eval_count": 147.64,
    "prompt_eval_duration": 17390000.0,
    "eval_count": 24.95,
    "eval_duration": 626420000.0
  },
  "meta_data_sd": {
    "done": 0.0,
    "total_duration": 1839381865.445276,
    "load_duration": 1795202909.94235,
    "prompt_eval_count": 1.2514234319608237,
    "prompt_eval_duration": 12789590.938088534,
    "eval_count": 2.0468009037016617,
    "eval_duration": 51412410.56005796
  },
  "prediction_accuracy": 0.0,
  "prediction_distribution": {},
  "actual_distribution": {},
  "confusion_matrix": {
    "tp": 0,
    "tn": 0,
    "fp": 0,
    "fn": 0
  },
  "auc_roc": 0.0
}