{
  "prompt_type": "PromptType.SYSTEM1",
  "model_name": "tulu3:8b-fp16",
  "start_time": "2025-01-06 00:56:32.091728",
  "end_time": "2025-01-06 00:57:17.099353",
  "total_attempts": 100,
  "successful_attempts": 100,
  "failed_attempts": 0,
  "timeout_attempts": 0,
  "avg_execution_time": 0.4483526873588562,
  "median_execution_time": 0.29594361782073975,
  "sd_execution_time": 1.4962106463802858,
  "timeout_stats": {
    "total_timeouts": 0,
    "avg_timeout_duration": 0.0,
    "max_timeout_duration": 0.0,
    "total_timeout_duration": 0.0
  },
  "meta_data_averages": {
    "done": 1.0,
    "total_duration": 446181514.53,
    "load_duration": 172022147.01,
    "prompt_eval_count": 131.62,
    "prompt_eval_duration": 10430000.0,
    "eval_count": 13.0,
    "eval_duration": 257430000.0
  },
  "meta_data_sd": {
    "done": 0.0,
    "total_duration": 1496137679.3584402,
    "load_duration": 1436553780.56713,
    "prompt_eval_count": 1.098943477926307,
    "prompt_eval_duration": 16585411.016488515,
    "eval_count": 0.0,
    "eval_duration": 6557061.117989561
  },
  "prediction_accuracy": 0.0,
  "prediction_distribution": {},
  "actual_distribution": {},
  "confusion_matrix": {
    "tp": 0,
    "tn": 0,
    "fp": 0,
    "fn": 0
  },
  "auc_roc": 0.0
}